LICENSE
MANIFEST.in
README.md
setup.cfg
setup.py
docassemble/__init__.py
docassemble.LAWVNameChange.egg-info/PKG-INFO
docassemble.LAWVNameChange.egg-info/SOURCES.txt
docassemble.LAWVNameChange.egg-info/dependency_links.txt
docassemble.LAWVNameChange.egg-info/namespace_packages.txt
docassemble.LAWVNameChange.egg-info/not-zip-safe
docassemble.LAWVNameChange.egg-info/top_level.txt
docassemble/LAWVNameChange/__init__.py
docassemble/LAWVNameChange/data/questions/name_change.yml
docassemble/LAWVNameChange/data/sources/README.md
docassemble/LAWVNameChange/data/static/README.md
docassemble/LAWVNameChange/data/templates/README.md
docassemble/LAWVNameChange/data/templates/name_change_instructions.pdf
docassemble/LAWVNameChange/data/templates/name_change_order.docx
docassemble/LAWVNameChange/data/templates/name_change_order_of_publication.docx
docassemble/LAWVNameChange/data/templates/name_change_petition_adult.docx