Metadata-Version: 2.1
Name: docassemble.LAWVNameChange
Version: 1.0.5
Summary: A docassemble extension to create a Name Change Petition packet suitable for court
Home-page: https://docassemble.org
Author: System Administrator
Author-email: dhenry@lawv.net
License: The MIT License (MIT)
Platform: UNKNOWN
License-File: LICENSE
